{
  "$schema": "http://json-schema.org/draft-04/schema#",
  "id": "https://raw.githubusercontent.com/woosmap/woosmap-json-schema/master/openingHours.json#",
  "title": "Opening Hours",
  "type": "object",
  "description": "The Opening Hours for an Asset",
  "properties": {
    "timezone": {
      "description": "String Timezone for the Opening Hours of an Assets (see https://en.wikipedia.org/wiki/List_of_tz_database_time_zones)",
      "type": "string"
    },
    "usual": {
      "type": "object",
      "description": "The Opening Hours for an Asset",
      "properties": {
        "default": {
          "description": "The Default opening Hours",
          "$ref": "https://raw.githubusercontent.com/woosmap/woosmap-json-schema/master/openingHoursInDay.json#"
        },
        "1": {
          "description": "The opening Hours for Monday",
          "$ref": "https://raw.githubusercontent.com/woosmap/woosmap-json-schema/master/openingHoursInDay.json#"
        },
        "2": {
          "description": "The opening Hours for Tuesday",
          "$ref": "https://raw.githubusercontent.com/woosmap/woosmap-json-schema/master/openingHoursInDay.json#"
        },
        "3": {
          "description": "The opening Hours for Wednesday",
          "$ref": "https://raw.githubusercontent.com/woosmap/woosmap-json-schema/master/openingHoursInDay.json#"
        },
        "4": {
          "description": "The opening Hours for Thirsday",
          "$ref": "https://raw.githubusercontent.com/woosmap/woosmap-json-schema/master/openingHoursInDay.json#"
        },
        "5": {
          "description": "The opening Hours for Friday",
          "$ref": "https://raw.githubusercontent.com/woosmap/woosmap-json-schema/master/openingHoursInDay.json#"
        },
        "6": {
          "description": "The opening Hours for Satruday",
          "$ref": "https://raw.githubusercontent.com/woosmap/woosmap-json-schema/master/openingHoursInDay.json#"
        },
        "7": {
          "description": "The opening Hours for Sunday",
          "$ref": "https://raw.githubusercontent.com/woosmap/woosmap-json-schema/master/openingHoursInDay.json#"
        }
      }
    },
    "special": {
      "description": "Special dates for opening and closing hours",
      "type": "object",
      "format": "date-time",
      "properties": {
        "type": "array",
        "items": {
          "$ref": "https://raw.githubusercontent.com/woosmap/woosmap-json-schema/master/openingHoursInDay.json#"
        }
      }
    }
  }
}

